swailing/__init__.py
swailing/logger.py
swailing/tests.py
swailing/token_bucket.py
swailing-0.1.2.dist-info/DESCRIPTION.rst
swailing-0.1.2.dist-info/METADATA
swailing-0.1.2.dist-info/RECORD
swailing-0.1.2.dist-info/WHEEL
swailing-0.1.2.dist-info/metadata.json
swailing-0.1.2.dist-info/top_level.txt
